{
  "pools": [
    {
      "rolls": 1,
      "entries": [
	  	{
          "type": "item",
          "name": "minecraft:jungle_sapling",
          "weight": 1000,
          "quality": -1000,
          "functions": [
			{
				"function": "minecraft:set_nbt",
				"tag": "{SkyblockMenu:1b,HideFlags:63}"
			},
			{
				"function": "set_name",
				"name": [{"text":"Foraging Collection","color":"green","italic":false}],
				"entity": "this"
			},
			{
				"function": "set_lore",
				"lore": [{"text":"View your Foraging Collection!","color":"gray","italic":false}, {"text":" "}, [{"text":"Collection Unlocked: ","color":"gray","italic":false},{"score":{"name":"@s","objective":"C_ForagingP"},"color":"yellow"},{"text":"%","color":"gold"}], [{"score":{"name":"@s","objective":"C_Foraging"},"italic":false,"color":"yellow"},{"text":"/","color":"gold","italic":false},{"text":"6","color":"yellow","italic":false}]],
				"entity": "this"
			}
          ]
        }
      ]
    }
  ]
}